__init__.py
crud.py
dbdef.py
main.py
models.py
schemas.py
FastAPIExample-0.0.6.dist-info/LICENSE
FastAPIExample-0.0.6.dist-info/METADATA
FastAPIExample-0.0.6.dist-info/WHEEL
FastAPIExample-0.0.6.dist-info/top_level.txt
FastAPIExample-0.0.6.dist-info/RECORD
