Metadata-Version: 2.1
Name: FastAPIExample
Version: 0.0.6
Summary: Exploring FastAPI
Author-email: Hendrik du Toit <hendrik@brightedge.co.za>
License: MIT License
Project-URL: Changelog, https://github.com/hendrikdutoit/FastAPIExample/blob/enhancement/master/CHANGES.md
Project-URL: Homepage, https://github.com/hendrikdutoit/FastAPIExample
Classifier: Development Status :: 2 - Pre-Alpha
Classifier: Intended Audience :: Developers
Classifier: Intended Audience :: Information Technology
Classifier: Topic :: Communications
Classifier: Topic :: Software Development
Classifier: Topic :: Internet :: WWW/HTTP
Classifier: License :: OSI Approved :: MIT License
Classifier: Programming Language :: Python :: 3.10
Classifier: Programming Language :: Python :: 3.11
Requires-Python: <3.12,>=3.10
License-File: LICENSE
Requires-Dist: fastapi
Requires-Dist: sqlalchemy
Provides-Extra: dev
Requires-Dist: git-it ; extra == 'dev'
Requires-Dist: pytest ; extra == 'dev'
Requires-Dist: pytest-cov ; extra == 'dev'
Requires-Dist: uvicorn ; extra == 'dev'
